{
  "lang":"en",
  "name":"pipeline",
  "version":"0.0.0",
  "spacy_version":">=3.8.13,<3.9.0",
  "description":"",
  "author":"",
  "email":"",
  "url":"",
  "license":"",
  "spacy_git_version":"fdca647",
  "vectors":{
    "width":0,
    "vectors":0,
    "keys":0,
    "name":null,
    "mode":"default"
  },
  "labels":{
    "tok2vec":[

    ],
    "ner":[
      "CERTIFICATE",
      "DATE",
      "DEGREE",
      "GPE",
      "JOB_TITLE",
      "LANGUAGE",
      "ORG",
      "SCHOOL"
    ]
  },
  "pipeline":[
    "tok2vec",
    "ner"
  ],
  "components":[
    "tok2vec",
    "ner"
  ],
  "disabled":[

  ],
  "performance":{
    "ents_f":0.347826087,
    "ents_p":0.8275862069,
    "ents_r":0.2201834862,
    "ents_per_type":{
      "LANGUAGE":{
        "p":1.0,
        "r":0.9166666667,
        "f":0.9565217391
      },
      "ORG":{
        "p":0.0,
        "r":0.0,
        "f":0.0
      },
      "DATE":{
        "p":0.0,
        "r":0.0,
        "f":0.0
      },
      "DEGREE":{
        "p":0.0,
        "r":0.0,
        "f":0.0
      },
      "GPE":{
        "p":0.0,
        "r":0.0,
        "f":0.0
      },
      "JOB_TITLE":{
        "p":0.1666666667,
        "r":0.0416666667,
        "f":0.0666666667
      },
      "SCHOOL":{
        "p":1.0,
        "r":0.0476190476,
        "f":0.0909090909
      }
    },
    "tok2vec_loss":126.5073014743,
    "ner_loss":863.2252807617
  }
}